L3/Ex3/lfsr.vhd
library IEEE;
use IEEE.STD_LOGIC_1164.ALL;
use IEEE.numeric_std.ALL;


entity lfsr is
	Port( 	clk : in  STD_LOGIC;
           	q 	: inout  STD_LOGIC_VECTOR(15 downto 0) := (OTHERS => '0')
		);
end lfsr;

ARCHITECTURE Behavioral OF lfsr IS
BEGIN
	PROCESS
	BEGIN
		q(15 downto 1) <= q(14 downto 0);
		q(0) <= not(q(15) XOR q(14) XOR q(13) XOR q(4));
		WAIT UNTIL clk'event AND clk='1';
	END PROCESS;
END Behavioral;

L3/Ex3/lfsr_tb.vhd
LIBRARY STD;
use std.textio.all;
LIBRARY ieee;
use ieee.std_logic_1164.ALL;
use ieee.numeric_std.ALL;


entity lfsr_tb is
end lfsr_tb;

ARCHITECTURE behavior of lfsr_tb is
    --UUT
    component lfsr is
		port(
				clk : in  STD_LOGIC;
				q 	: inout  STD_LOGIC_VECTOR(15 downto 0) := (others => '0')
			);
    end component;

    signal clk 	: STD_LOGIC := '0';
    signal q 	: STD_LOGIC_VECTOR(15 downto 0);

    constant clk_period : time := 20 ns;

    BEGIN
        uut: lfsr port map(
			clk => clk,
			q => q
        );

        clk_process: PROCESS
        BEGIN
			clk <= not clk;
    		wait for clk_period/2;
        END PROCESS;

		watch: PROCESS(clk)
		  variable ln: LINE;
		  variable b: STRING(1 to 3);
		BEGIN
		IF rising_edge(clk) THEN
		  for i in 15 downto 0 LOOP
		    b := STD_LOGIC'Image(q(i));
		    WRITE(ln, b(2));
		  END LOOP;
		  WRITELINE(output, ln);
		END IF;
	END PROCESS;
END;

L3/Ex3/lfsr.vcd
$date
  Wed Apr 21 09:52:33 2021
$end
$version
  GHDL v0
$end
$timescale
  1 fs
$end
$scope module standard $end
$upscope $end
$scope module textio $end
$upscope $end
$scope module std_logic_1164 $end
$upscope $end
$scope module numeric_std $end
$upscope $end
$scope module lfsr_tb $end
$var reg 1 ! clk $end
$var reg 16 " q[15:0] $end
$scope module uut $end
$var reg 1 # clk $end
$var reg 16 $ q[15:0] $end
$upscope $end
$upscope $end
$enddefinitions $end
#0
1!
b0000000000000011 "
1#
b0000000000000011 $
#10000000
0!
0#
#20000000
1!
b0000000000000111 "
1#
b0000000000000111 $
#30000000
0!
0#
#40000000
1!
b0000000000001111 "
1#
b0000000000001111 $
#50000000
0!
0#
#60000000
1!
b0000000000011111 "
1#
b0000000000011111 $
#70000000
0!
0#
#80000000
1!
b0000000000111110 "
1#
b0000000000111110 $
#90000000
0!
0#
#100000000
1!
b0000000001111100 "
1#
b0000000001111100 $
#110000000
0!
0#
#120000000
1!
b0000000011111000 "
1#
b0000000011111000 $
#130000000
0!
0#
#140000000
1!
b0000000111110000 "
1#
b0000000111110000 $
#150000000
0!
0#
#160000000
1!
b0000001111100000 "
1#
b0000001111100000 $
#170000000
0!
0#
#180000000
1!
b0000011111000001 "
1#
b0000011111000001 $
#190000000
0!
0#
#200000000
1!
b0000111110000011 "
1#
b0000111110000011 $
#210000000
0!
0#
#220000000
1!
b0001111100000111 "
1#
b0001111100000111 $
#230000000
0!
0#
#240000000
1!
b0011111000001111 "
1#
b0011111000001111 $
#250000000
0!
0#
#260000000
1!
b0111110000011110 "
1#
b0111110000011110 $
#270000000
0!
0#
#280000000
1!
b1111100000111100 "
1#
b1111100000111100 $
#290000000
0!
0#
#300000000
1!
b1111000001111001 "
1#
b1111000001111001 $
#310000000
0!
0#
#320000000
1!
b1110000011110011 "
1#
b1110000011110011 $
#330000000
0!
0#
#340000000
1!
b1100000111100111 "
1#
b1100000111100111 $
#350000000
0!
0#
#360000000
1!
b1000001111001111 "
1#
b1000001111001111 $
#370000000
0!
0#
#380000000
1!
b0000011110011110 "
1#
b0000011110011110 $
#390000000
0!
0#
#400000000
1!
b0000111100111100 "
1#
b0000111100111100 $
#410000000
0!
0#
#420000000
1!
b0001111001111000 "
1#
b0001111001111000 $
#430000000
0!
0#
#440000000
1!
b0011110011110000 "
1#
b0011110011110000 $
#450000000
0!
0#
#460000000
1!
b0111100111100001 "
1#
b0111100111100001 $
#470000000
0!
0#
#480000000
1!
b1111001111000011 "
1#
b1111001111000011 $
#490000000
0!
0#
#500000000
1!
b1110011110000110 "
1#
b1110011110000110 $
#510000000
0!
0#
#520000000
1!
b1100111100001100 "
1#
b1100111100001100 $
#530000000
0!
0#
#540000000
1!
b1001111000011001 "
1#
b1001111000011001 $
#550000000
0!
0#
#560000000
1!
b0011110000110011 "
1#
b0011110000110011 $
#570000000
0!
0#
#580000000
1!
b0111100001100111 "
1#
b0111100001100111 $
#590000000
0!
0#
#600000000
1!
b1111000011001111 "
1#
b1111000011001111 $
#610000000
0!
0#
#620000000
1!
b1110000110011110 "
1#
b1110000110011110 $
#630000000
0!
0#
#640000000
1!
b1100001100111101 "
1#
b1100001100111101 $
#650000000
0!
0#
#660000000
1!
b1000011001111010 "
1#
b1000011001111010 $
#670000000
0!
0#
#680000000
1!
b0000110011110101 "
1#
b0000110011110101 $
#690000000
0!
0#
#700000000
1!
b0001100111101010 "
1#
b0001100111101010 $
#710000000
0!
0#
#720000000
1!
b0011001111010101 "
1#
b0011001111010101 $
#730000000
0!
0#
#740000000
1!
b0110011110101011 "
1#
b0110011110101011 $
#750000000
0!
0#
#760000000
1!
b1100111101010111 "
1#
b1100111101010111 $
#770000000
0!
0#
#780000000
1!
b1001111010101110 "
1#
b1001111010101110 $
#790000000
0!
0#
#800000000
1!
b0011110101011100 "
1#
b0011110101011100 $
#810000000
0!
0#
#820000000
1!
b0111101010111001 "
1#
b0111101010111001 $
#830000000
0!
0#
#840000000
1!
b1111010101110010 "
1#
b1111010101110010 $
#850000000
0!
0#
#860000000
1!
b1110101011100101 "
1#
b1110101011100101 $
#870000000
0!
0#
#880000000
1!
b1101010111001010 "
1#
b1101010111001010 $
#890000000
0!
0#
#900000000
1!
b1010101110010101 "
1#
b1010101110010101 $
#910000000
0!
0#
#920000000
1!
b0101011100101010 "
1#
b0101011100101010 $
#930000000
0!
0#
#940000000
1!
b1010111001010100 "
1#
b1010111001010100 $
#950000000
0!
0#
#960000000
1!
b0101110010101000 "
1#
b0101110010101000 $
#970000000
0!
0#
#980000000
1!
b1011100101010000 "
1#
b1011100101010000 $
#990000000
0!
0#
#1000000000
1!
b0111001010100000 "
1#
b0111001010100000 $
#1010000000
0!
0#
#1020000000
1!
b1110010101000001 "
1#
b1110010101000001 $
#1030000000
0!
0#
#1040000000
1!
b1100101010000010 "
1#
b1100101010000010 $
#1050000000
0!
0#
#1060000000
1!
b1001010100000101 "
1#
b1001010100000101 $
#1070000000
0!
0#
#1080000000
1!
b0010101000001010 "
1#
b0010101000001010 $
#1090000000
0!
0#
#1100000000
1!
b0101010000010100 "
1#
b0101010000010100 $
#1110000000
0!
0#
#1120000000
1!
b1010100000101001 "
1#
b1010100000101001 $
#1130000000
0!
0#
#1140000000
1!
b0101000001010011 "
1#
b0101000001010011 $
#1150000000
0!
0#
#1160000000
1!
b1010000010100111 "
1#
b1010000010100111 $
#1170000000
0!
0#
#1180000000
1!
b0100000101001111 "
1#
b0100000101001111 $
#1190000000
0!
0#
#1200000000
1!
b1000001010011110 "
1#
b1000001010011110 $
#1210000000
0!
0#
#1220000000
1!
b0000010100111101 "
1#
b0000010100111101 $
#1230000000
0!
0#
#1240000000
1!
b0000101001111010 "
1#
b0000101001111010 $
#1250000000
0!
0#
#1260000000
1!
b0001010011110100 "
1#
b0001010011110100 $
#1270000000
0!
0#
#1280000000
1!
b0010100111101000 "
1#
b0010100111101000 $
#1290000000
0!
0#
#1300000000
1!
b0101001111010000 "
1#
b0101001111010000 $
#1310000000
0!
0#
#1320000000
1!
b1010011110100001 "
1#
b1010011110100001 $
#1330000000
0!
0#
#1340000000
1!
b0100111101000011 "
1#
b0100111101000011 $
#1350000000
0!
0#
#1360000000
1!
b1001111010000110 "
1#
b1001111010000110 $
#1370000000
0!
0#
#1380000000
1!
b0011110100001100 "
1#
b0011110100001100 $
#1390000000
0!
0#
#1400000000
1!
b0111101000011000 "
1#
b0111101000011000 $
#1410000000
0!
0#
#1420000000
1!
b1111010000110000 "
1#
b1111010000110000 $
#1430000000
0!
0#
#1440000000
1!
b1110100001100001 "
1#
b1110100001100001 $
#1450000000
0!
0#
#1460000000
1!
b1101000011000010 "
1#
b1101000011000010 $
#1470000000
0!
0#
#1480000000
1!
b1010000110000101 "
1#
b1010000110000101 $
#1490000000
0!
0#
#1500000000
1!
b0100001100001011 "
1#
b0100001100001011 $
#1510000000
0!
0#
#1520000000
1!
b1000011000010110 "
1#
b1000011000010110 $
#1530000000
0!
0#
#1540000000
1!
b0000110000101101 "
1#
b0000110000101101 $
#1550000000
0!
0#
#1560000000
1!
b0001100001011011 "
1#
b0001100001011011 $
#1570000000
0!
0#
#1580000000
1!
b0011000010110110 "
1#
b0011000010110110 $
#1590000000
0!
0#
#1600000000
1!
b0110000101101101 "
1#
b0110000101101101 $
#1610000000
0!
0#
#1620000000
1!
b1100001011011011 "
1#
b1100001011011011 $
#1630000000
0!
0#
#1640000000
1!
b1000010110110110 "
1#
b1000010110110110 $
#1650000000
0!
0#
#1660000000
1!
b0000101101101101 "
1#
b0000101101101101 $
#1670000000
0!
0#
#1680000000
1!
b0001011011011011 "
1#
b0001011011011011 $
#1690000000
0!
0#
#1700000000
1!
b0010110110110110 "
1#
b0010110110110110 $
#1710000000
0!
0#
#1720000000
1!
b0101101101101101 "
1#
b0101101101101101 $
#1730000000
0!
0#
#1740000000
1!
b1011011011011010 "
1#
b1011011011011010 $
#1750000000
0!
0#
#1760000000
1!
b0110110110110100 "
1#
b0110110110110100 $
#1770000000
0!
0#
#1780000000
1!
b1101101101101000 "
1#
b1101101101101000 $
#1790000000
0!
0#
#1800000000
1!
b1011011011010001 "
1#
b1011011011010001 $
#1810000000
0!
0#
#1820000000
1!
b0110110110100010 "
1#
b0110110110100010 $
#1830000000
0!
0#
#1840000000
1!
b1101101101000101 "
1#
b1101101101000101 $
#1850000000
0!
0#
#1860000000
1!
b1011011010001011 "
1#
b1011011010001011 $
#1870000000
0!
0#
#1880000000
1!
b0110110100010111 "
1#
b0110110100010111 $
#1890000000
0!
0#
#1900000000
1!
b1101101000101110 "
1#
b1101101000101110 $
#1910000000
0!
0#
#1920000000
1!
b1011010001011101 "
1#
b1011010001011101 $
#1930000000
0!
0#
#1940000000
1!
b0110100010111010 "
1#
b0110100010111010 $
#1950000000
0!
0#
#1960000000
1!
b1101000101110100 "
1#
b1101000101110100 $
#1970000000
0!
0#
#1980000000
1!
b1010001011101000 "
1#
b1010001011101000 $
#1990000000
0!
0#
#2000000000
1!
b0100010111010001 "
1#
b0100010111010001 $
#2010000000
0!
0#
#2020000000
1!
b1000101110100011 "
1#
b1000101110100011 $
#2030000000
0!
0#
#2040000000
1!
b0001011101000110 "
1#
b0001011101000110 $
#2050000000
0!
0#
#2060000000
1!
b0010111010001101 "
1#
b0010111010001101 $
#2070000000
0!
0#
#2080000000
1!
b0101110100011010 "
1#
b0101110100011010 $
#2090000000
0!
0#
#2100000000
1!
b1011101000110101 "
1#
b1011101000110101 $
#2110000000
0!
0#
#2120000000
1!
b0111010001101010 "
1#
b0111010001101010 $
#2130000000
0!
0#
#2140000000
1!
b1110100011010101 "
1#
b1110100011010101 $
#2150000000
0!
0#
#2160000000
1!
b1101000110101011 "
1#
b1101000110101011 $
#2170000000
0!
0#
#2180000000
1!
b1010001101010111 "
1#
b1010001101010111 $
#2190000000
0!
0#
#2200000000
1!
b0100011010101110 "
1#
b0100011010101110 $
#2210000000
0!
0#
#2220000000
1!
b1000110101011100 "
1#
b1000110101011100 $
#2230000000
0!
0#
#2240000000
1!
b0001101010111001 "
1#
b0001101010111001 $
#2250000000
0!
0#
#2260000000
1!
b0011010101110010 "
1#
b0011010101110010 $
#2270000000
0!
0#
#2280000000
1!
b0110101011100101 "
1#
b0110101011100101 $
#2290000000
0!
0#
#2300000000
1!
b1101010111001011 "
1#
b1101010111001011 $
#2310000000
0!
0#
#2320000000
1!
b1010101110010111 "
1#
b1010101110010111 $
#2330000000
0!
0#
#2340000000
1!
b0101011100101110 "
1#
b0101011100101110 $
#2350000000
0!
0#
#2360000000
1!
b1010111001011100 "
1#
b1010111001011100 $
#2370000000
0!
0#
#2380000000
1!
b0101110010111000 "
1#
b0101110010111000 $
#2390000000
0!
0#
#2400000000
1!
b1011100101110001 "
1#
b1011100101110001 $
#2410000000
0!
0#
#2420000000
1!
b0111001011100010 "
1#
b0111001011100010 $
#2430000000
0!
0#
#2440000000
1!
b1110010111000101 "
1#
b1110010111000101 $
#2450000000
0!
0#
#2460000000
1!
b1100101110001010 "
1#
b1100101110001010 $
#2470000000
0!
0#
#2480000000
1!
b1001011100010101 "
1#
b1001011100010101 $
#2490000000
0!
0#
#2500000000
1!
b0010111000101011 "
1#
b0010111000101011 $
#2510000000
0!
0#
#2520000000
1!
b0101110001010110 "
1#
b0101110001010110 $
#2530000000
0!
0#
#2540000000
1!
b1011100010101101 "
1#
b1011100010101101 $
#2550000000
0!
0#
#2560000000
1!
b0111000101011011 "
1#
b0111000101011011 $
#2570000000
0!
0#
#2580000000
1!
b1110001010110110 "
1#
b1110001010110110 $
#2590000000
0!
0#
#2600000000
1!
b1100010101101101 "
1#
b1100010101101101 $
#2610000000
0!
0#
#2620000000
1!
b1000101011011011 "
1#
b1000101011011011 $
#2630000000
0!
0#
#2640000000
1!
b0001010110110111 "
1#
b0001010110110111 $
#2650000000
0!
0#
#2660000000
1!
b0010101101101110 "
1#
b0010101101101110 $
#2670000000
0!
0#
#2680000000
1!
b0101011011011100 "
1#
b0101011011011100 $
#2690000000
0!
0#
#2700000000
1!
b1010110110111001 "
1#
b1010110110111001 $
#2710000000
0!
0#
#2720000000
1!
b0101101101110010 "
1#
b0101101101110010 $
#2730000000
0!
0#
#2740000000
1!
b1011011011100101 "
1#
b1011011011100101 $
#2750000000
0!
0#
#2760000000
1!
b0110110111001011 "
1#
b0110110111001011 $
#2770000000
0!
0#
#2780000000
1!
b1101101110010111 "
1#
b1101101110010111 $
#2790000000
0!
0#
#2800000000
1!
b1011011100101110 "
1#
b1011011100101110 $
#2810000000
0!
0#
#2820000000
1!
b0110111001011101 "
1#
b0110111001011101 $
#2830000000
0!
0#
#2840000000
1!
b1101110010111010 "
1#
b1101110010111010 $
#2850000000
0!
0#
#2860000000
1!
b1011100101110100 "
1#
b1011100101110100 $
#2870000000
0!
0#
#2880000000
1!
b0111001011101000 "
1#
b0111001011101000 $
#2890000000
0!
0#
#2900000000
1!
b1110010111010001 "
1#
b1110010111010001 $
#2910000000
0!
0#
#2920000000
1!
b1100101110100011 "
1#
b1100101110100011 $
#2930000000
0!
0#
#2940000000
1!
b1001011101000111 "
1#
b1001011101000111 $
#2950000000
0!
0#
#2960000000
1!
b0010111010001110 "
1#
b0010111010001110 $
#2970000000
0!
0#
#2980000000
1!
b0101110100011100 "
1#
b0101110100011100 $
#2990000000
0!
0#
#3000000000
1!
b1011101000111001 "
1#
b1011101000111001 $
#3010000000
0!
0#
#3020000000
1!
b0111010001110010 "
1#
b0111010001110010 $
#3030000000
0!
0#
#3040000000
1!
b1110100011100100 "
1#
b1110100011100100 $
#3050000000
0!
0#
#3060000000
1!
b1101000111001000 "
1#
b1101000111001000 $
#3070000000
0!
0#
#3080000000
1!
b1010001110010001 "
1#
b1010001110010001 $
#3090000000
0!
0#
#3100000000
1!
b0100011100100010 "
1#
b0100011100100010 $
#3110000000
0!
0#
#3120000000
1!
b1000111001000100 "
1#
b1000111001000100 $
#3130000000
0!
0#
#3140000000
1!
b0001110010001000 "
1#
b0001110010001000 $
#3150000000
0!
0#
#3160000000
1!
b0011100100010001 "
1#
b0011100100010001 $
#3170000000
0!
0#
#3180000000
1!
b0111001000100011 "
1#
b0111001000100011 $
#3190000000
0!
0#
#3200000000
1!
b1110010001000111 "
1#
b1110010001000111 $
#3210000000
0!
0#
#3220000000
1!
b1100100010001110 "
1#
b1100100010001110 $
#3230000000
0!
0#
#3240000000
1!
b1001000100011101 "
1#
b1001000100011101 $
#3250000000
0!
0#
#3260000000
1!
b0010001000111011 "
1#
b0010001000111011 $
#3270000000
0!
0#
#3280000000
1!
b0100010001110111 "
1#
b0100010001110111 $
#3290000000
0!
0#
#3300000000
1!
b1000100011101111 "
1#
b1000100011101111 $
#3310000000
0!
0#
#3320000000
1!
b0001000111011110 "
1#
b0001000111011110 $
#3330000000
0!
0#
#3340000000
1!
b0010001110111100 "
1#
b0010001110111100 $
#3350000000
0!
0#
#3360000000
1!
b0100011101111001 "
1#
b0100011101111001 $
#3370000000
0!
0#
#3380000000
1!
b1000111011110011 "
1#
b1000111011110011 $
#3390000000
0!
0#
#3400000000
1!
b0001110111100111 "
1#
b0001110111100111 $
#3410000000
0!
0#
#3420000000
1!
b0011101111001111 "
1#
b0011101111001111 $
#3430000000
0!
0#
#3440000000
1!
b0111011110011110 "
1#
b0111011110011110 $
#3450000000
0!
0#
#3460000000
1!
b1110111100111100 "
1#
b1110111100111100 $
#3470000000
0!
0#
#3480000000
1!
b1101111001111001 "
1#
b1101111001111001 $
#3490000000
0!
0#
#3500000000
1!
b1011110011110010 "
1#
b1011110011110010 $
#3510000000
0!
0#
#3520000000
1!
b0111100111100100 "
1#
b0111100111100100 $
#3530000000
0!
0#
#3540000000
1!
b1111001111001001 "
1#
b1111001111001001 $
#3550000000
0!
0#
#3560000000
1!
b1110011110010010 "
1#
b1110011110010010 $
#3570000000
0!
0#
#3580000000
1!
b1100111100100101 "
1#
b1100111100100101 $
#3590000000
0!
0#
#3600000000
1!
b1001111001001011 "
1#
b1001111001001011 $
#3610000000
0!
0#
#3620000000
1!
b0011110010010110 "
1#
b0011110010010110 $
#3630000000
0!
0#
#3640000000
1!
b0111100100101101 "
1#
b0111100100101101 $
#3650000000
0!
0#
#3660000000
1!
b1111001001011011 "
1#
b1111001001011011 $
#3670000000
0!
0#
#3680000000
1!
b1110010010110111 "
1#
b1110010010110111 $
#3690000000
0!
0#
#3700000000
1!
b1100100101101111 "
1#
b1100100101101111 $
#3710000000
0!
0#
#3720000000
1!
b1001001011011111 "
1#
b1001001011011111 $
#3730000000
0!
0#
#3740000000
1!
b0010010110111111 "
1#
b0010010110111111 $
#3750000000
0!
0#
#3760000000
1!
b0100101101111111 "
1#
b0100101101111111 $
#3770000000
0!
0#
#3780000000
1!
b1001011011111111 "
1#
b1001011011111111 $
#3790000000
0!
0#
#3800000000
1!
b0010110111111111 "
1#
b0010110111111111 $
#3810000000
0!
0#
#3820000000
1!
b0101101111111111 "
1#
b0101101111111111 $
#3830000000
0!
0#
#3840000000
1!
b1011011111111111 "
1#
b1011011111111111 $
#3850000000
0!
0#
#3860000000
1!
b0110111111111110 "
1#
b0110111111111110 $
#3870000000
0!
0#
#3880000000
1!
b1101111111111100 "
1#
b1101111111111100 $
#3890000000
0!
0#
#3900000000
1!
b1011111111111000 "
1#
b1011111111111000 $
#3910000000
0!
0#
#3920000000
1!
b0111111111110000 "
1#
b0111111111110000 $
#3930000000
0!
0#
#3940000000
1!
b1111111111100000 "
1#
b1111111111100000 $
#3950000000
0!
0#
#3960000000
1!
b1111111111000000 "
1#
b1111111111000000 $
#3970000000
0!
0#
#3980000000
1!
b1111111110000000 "
1#
b1111111110000000 $
#3990000000
0!
0#
#4000000000
1!
b1111111100000000 "
1#
b1111111100000000 $
#4010000000
0!
0#
#4020000000
1!
b1111111000000000 "
1#
b1111111000000000 $
#4030000000
0!
0#
#4040000000
1!
b1111110000000000 "
1#
b1111110000000000 $
#4050000000
0!
0#
#4060000000
1!
b1111100000000000 "
1#
b1111100000000000 $
#4070000000
0!
0#
#4080000000
1!
b1111000000000000 "
1#
b1111000000000000 $
#4090000000
0!
0#
#4100000000
1!
b1110000000000000 "
1#
b1110000000000000 $
#4110000000
0!
0#
#4120000000
1!
b1100000000000000 "
1#
b1100000000000000 $
#4130000000
0!
0#
#4140000000
1!
b1000000000000001 "
1#
b1000000000000001 $
#4150000000
0!
0#
#4160000000
1!
b0000000000000010 "
1#
b0000000000000010 $
#4170000000
0!
0#
#4180000000
1!
b0000000000000101 "
1#
b0000000000000101 $
#4190000000
0!
0#
#4200000000
1!
b0000000000001011 "
1#
b0000000000001011 $
#4210000000
0!
0#
#4220000000
1!
b0000000000010111 "
1#
b0000000000010111 $
#4230000000
0!
0#
#4240000000
1!
b0000000000101110 "
1#
b0000000000101110 $
#4250000000
0!
0#
#4260000000
1!
b0000000001011101 "
1#
b0000000001011101 $
#4270000000
0!
0#
#4280000000
1!
b0000000010111010 "
1#
b0000000010111010 $
#4290000000
0!
0#
#4300000000
1!
b0000000101110100 "
1#
b0000000101110100 $
#4310000000
0!
0#
#4320000000
1!
b0000001011101000 "
1#
b0000001011101000 $
#4330000000
0!
0#
#4340000000
1!
b0000010111010001 "
1#
b0000010111010001 $
#4350000000
0!
0#
#4360000000
1!
b0000101110100010 "
1#
b0000101110100010 $
#4370000000
0!
0#
#4380000000
1!
b0001011101000101 "
1#
b0001011101000101 $
#4390000000
0!
0#
#4400000000
1!
b0010111010001011 "
1#
b0010111010001011 $
#4410000000
0!
0#
#4420000000
1!
b0101110100010110 "
1#
b0101110100010110 $
#4430000000
0!
0#
#4440000000
1!
b1011101000101101 "
1#
b1011101000101101 $
#4450000000
0!
0#
#4460000000
1!
b0111010001011011 "
1#
b0111010001011011 $
#4470000000
0!
0#
#4480000000
1!
b1110100010110110 "
1#
b1110100010110110 $
#4490000000
0!
0#
#4500000000
1!
b1101000101101101 "
1#
b1101000101101101 $
#4510000000
0!
0#
#4520000000
1!
b1010001011011011 "
1#
b1010001011011011 $
#4530000000
0!
0#
#4540000000
1!
b0100010110110110 "
1#
b0100010110110110 $
#4550000000
0!
0#
#4560000000
1!
b1000101101101101 "
1#
b1000101101101101 $
#4570000000
0!
0#
#4580000000
1!
b0001011011011010 "
1#
b0001011011011010 $
#4590000000
0!
0#
#4600000000
1!
b0010110110110100 "
1#
b0010110110110100 $
#4610000000
0!
0#
#4620000000
1!
b0101101101101001 "
1#
b0101101101101001 $
#4630000000
0!
0#
#4640000000
1!
b1011011011010010 "
1#
b1011011011010010 $
#4650000000
0!
0#
#4660000000
1!
b0110110110100100 "
1#
b0110110110100100 $
#4670000000
0!
0#
#4680000000
1!
b1101101101001001 "
1#
b1101101101001001 $
#4690000000
0!
0#
#4700000000
1!
b1011011010010011 "
1#
b1011011010010011 $
#4710000000
0!
0#
#4720000000
1!
b0110110100100110 "
1#
b0110110100100110 $
#4730000000
0!
0#
#4740000000
1!
b1101101001001101 "
1#
b1101101001001101 $
#4750000000
0!
0#
#4760000000
1!
b1011010010011011 "
1#
b1011010010011011 $
#4770000000
0!
0#
#4780000000
1!
b0110100100110110 "
1#
b0110100100110110 $
#4790000000
0!
0#
#4800000000
1!
b1101001001101100 "
1#
b1101001001101100 $
#4810000000
0!
0#
#4820000000
1!
b1010010011011001 "
1#
b1010010011011001 $
#4830000000
0!
0#
#4840000000
1!
b0100100110110010 "
1#
b0100100110110010 $
#4850000000
0!
0#
#4860000000
1!
b1001001101100101 "
1#
b1001001101100101 $
#4870000000
0!
0#
#4880000000
1!
b0010011011001010 "
1#
b0010011011001010 $
#4890000000
0!
0#
#4900000000
1!
b0100110110010100 "
1#
b0100110110010100 $
#4910000000
0!
0#
#4920000000
1!
b1001101100101001 "
1#
b1001101100101001 $
#4930000000
0!
0#
#4940000000
1!
b0011011001010010 "
1#
b0011011001010010 $
#4950000000
0!
0#
#4960000000
1!
b0110110010100101 "
1#
b0110110010100101 $
#4970000000
0!
0#
#4980000000
1!
b1101100101001011 "
1#
b1101100101001011 $
#4990000000
0!
0#
#5000000000
1!
b1011001010010111 "
1#
b1011001010010111 $
#5010000000
0!
0#
#5020000000
1!
b0110010100101110 "
1#
b0110010100101110 $
#5030000000
0!
0#
#5040000000
1!
b1100101001011101 "
1#
b1100101001011101 $
#5050000000
0!
0#
#5060000000
1!
b1001010010111010 "
1#
b1001010010111010 $
#5070000000
0!
0#
#5080000000
1!
b0010100101110101 "
1#
b0010100101110101 $
#5090000000
0!
0#
#5100000000
1!
b0101001011101011 "
1#
b0101001011101011 $
#5110000000
0!
0#
#5120000000
1!
b1010010111010110 "
1#
b1010010111010110 $
#5130000000
0!
0#
#5140000000
1!
b0100101110101100 "
1#
b0100101110101100 $
#5150000000
0!
0#
#5160000000
1!
b1001011101011000 "
1#
b1001011101011000 $
#5170000000
0!
0#
#5180000000
1!
b0010111010110001 "
1#
b0010111010110001 $
#5190000000
0!
0#
#5200000000
1!
b0101110101100011 "
1#
b0101110101100011 $
#5210000000
0!
0#
#5220000000
1!
b1011101011000110 "
1#
b1011101011000110 $
#5230000000
0!
0#
#5240000000
1!
b0111010110001101 "
1#
b0111010110001101 $
#5250000000
0!
0#
#5260000000
1!
b1110101100011011 "
1#
b1110101100011011 $
#5270000000
0!
0#
#5280000000
1!
b1101011000110111 "
1#
b1101011000110111 $
#5290000000
0!
0#
#5300000000
1!
b1010110001101110 "
1#
b1010110001101110 $
#5310000000
0!
0#
#5320000000
1!
b0101100011011101 "
1#
b0101100011011101 $
#5330000000
0!
0#
#5340000000
1!
b1011000110111011 "
1#
b1011000110111011 $
#5350000000
0!
0#
#5360000000
1!
b0110001101110110 "
1#
b0110001101110110 $
#5370000000
0!
0#
#5380000000
1!
b1100011011101100 "
1#
b1100011011101100 $
#5390000000
0!
0#
#5400000000
1!
b1000110111011001 "
1#
b1000110111011001 $
#5410000000
0!
0#
#5420000000
1!
b0001101110110011 "
1#
b0001101110110011 $
#5430000000
0!
0#
#5440000000
1!
b0011011101100110 "
1#
b0011011101100110 $
#5450000000
0!
0#
#5460000000
1!
b0110111011001100 "
1#
b0110111011001100 $
#5470000000
0!
0#
#5480000000
1!
b1101110110011001 "
1#
b1101110110011001 $
#5490000000
0!
0#
#5500000000
1!
b1011101100110010 "
1#
b1011101100110010 $
#5510000000
0!
0#
#5520000000
1!
b0111011001100100 "
1#
b0111011001100100 $
#5530000000
0!
0#
#5540000000
1!
b1110110011001001 "
1#
b1110110011001001 $
#5550000000
0!
0#
#5560000000
1!
b1101100110010010 "
1#
b1101100110010010 $
#5570000000
0!
0#
#5580000000
1!
b1011001100100100 "
1#
b1011001100100100 $
#5590000000
0!
0#
#5600000000
1!
b0110011001001001 "
1#
b0110011001001001 $
#5610000000
0!
0#
#5620000000
1!
b1100110010010011 "
1#
b1100110010010011 $
#5630000000
0!
0#
#5640000000
1!
b1001100100100110 "
1#
b1001100100100110 $
#5650000000
0!
0#
#5660000000
1!
b0011001001001100 "
1#
b0011001001001100 $
#5670000000
0!
0#
#5680000000
1!
b0110010010011000 "
1#
b0110010010011000 $
#5690000000
0!
0#
#5700000000
1!
b1100100100110000 "
1#
b1100100100110000 $
#5710000000
0!
0#
#5720000000
1!
b1001001001100000 "
1#
b1001001001100000 $
#5730000000
0!
0#
#5740000000
1!
b0010010011000000 "
1#
b0010010011000000 $
#5750000000
0!
0#
#5760000000
1!
b0100100110000000 "
1#
b0100100110000000 $
#5770000000
0!
0#
#5780000000
1!
b1001001100000000 "
1#
b1001001100000000 $
#5790000000
0!
0#
#5800000000
1!
b0010011000000000 "
1#
b0010011000000000 $
#5810000000
0!
0#
#5820000000
1!
b0100110000000000 "
1#
b0100110000000000 $
#5830000000
0!
0#
#5840000000
1!
b1001100000000000 "
1#
b1001100000000000 $
#5850000000
0!
0#
#5860000000
1!
b0011000000000000 "
1#
b0011000000000000 $
#5870000000
0!
0#
#5880000000
1!
b0110000000000000 "
1#
b0110000000000000 $
#5890000000
0!
0#
#5900000000
1!
b1100000000000001 "
1#
b1100000000000001 $
#5910000000
0!
0#
#5920000000
1!
b1000000000000011 "
1#
b1000000000000011 $
#5930000000
0!
0#
#5940000000
1!
b0000000000000110 "
1#
b0000000000000110 $
#5950000000
0!
0#
#5960000000
1!
b0000000000001101 "
1#
b0000000000001101 $
#5970000000
0!
0#
#5980000000
1!
b0000000000011011 "
1#
b0000000000011011 $
#5990000000
0!
0#
#6000000000
1!
b0000000000110110 "
1#
b0000000000110110 $
#6010000000
0!
0#
#6020000000
1!
b0000000001101100 "
1#
b0000000001101100 $
#6030000000
0!
0#
#6040000000
1!
b0000000011011001 "
1#
b0000000011011001 $
#6050000000
0!
0#
#6060000000
1!
b0000000110110010 "
1#
b0000000110110010 $
#6070000000
0!
0#
#6080000000
1!
b0000001101100100 "
1#
b0000001101100100 $
#6090000000
0!
0#
#6100000000
1!
b0000011011001001 "
1#
b0000011011001001 $
#6110000000
0!
0#
#6120000000
1!
b0000110110010011 "
1#
b0000110110010011 $
#6130000000
0!
0#
#6140000000
1!
b0001101100100110 "
1#
b0001101100100110 $
#6150000000
0!
0#
#6160000000
1!
b0011011001001101 "
1#
b0011011001001101 $
#6170000000
0!
0#
#6180000000
1!
b0110110010011010 "
1#
b0110110010011010 $
#6190000000
0!
0#
#6200000000
1!
b1101100100110100 "
1#
b1101100100110100 $
#6210000000
0!
0#
#6220000000
1!
b1011001001101000 "
1#
b1011001001101000 $
#6230000000
0!
0#
#6240000000
1!
b0110010011010001 "
1#
b0110010011010001 $
#6250000000
0!
0#
#6260000000
1!
b1100100110100010 "
1#
b1100100110100010 $
#6270000000
0!
0#
#6280000000
1!
b1001001101000101 "
1#
b1001001101000101 $
#6290000000
0!
0#
#6300000000
1!
b0010011010001010 "
1#
b0010011010001010 $
#6310000000
0!
0#
#6320000000
1!
b0100110100010100 "
1#
b0100110100010100 $
#6330000000
0!
0#
#6340000000
1!
b1001101000101001 "
1#
b1001101000101001 $
#6350000000
0!
0#
#6360000000
1!
b0011010001010010 "
1#
b0011010001010010 $
#6370000000
0!
0#
