L2/Subtractor/adder.vhdl
library ieee;
use ieee.std_logic_1164.all;

entity adder is
	-- `i0`, `i1` and the carry-in `ci` are inputs of the adder.
	-- `s` is the sum output, `co` is the carry-out.
	port (	i0, i1 : in std_logic; 
			ci : in std_logic; 
			s : out std_logic; 
			co : out std_logic);
end adder;

architecture rtl of adder is
begin
	--  This full-adder architecture contains two concurrent assignment.
	--  Compute the sum.
	s <= i0 xor i1 xor ci after 1 ns;
	--  Compute the carry.
	co <= (i0 and i1) or (i0 and ci) or (i1 and ci) after 1 ns;
end rtl;

L2/Subtractor/sub.vhdl
library ieee;
use ieee.std_logic_1164.all;
use ieee.numeric_std.all;

entity subtractor is
	generic(width : integer := 5);
	port( 
		op 	: in std_logic; 
		a,b : in unsigned(width-1 downto 0); 
		x 	: out unsigned(width-1 downto 0); 
		err : out std_logic
	);
end subtractor;

architecture Behavioral of subtractor is
	component adder
		port(
			i0, i1 	: in std_logic; 
			ci 		: in std_logic; 
			s 		: out std_logic; 
			co 		: out std_logic
		);
	end component; 

	constant zeros		: unsigned(width-1 downto 0) := (others => '0');
	signal carryOuts 	: unsigned(width downto 0) := (others => '0');
	signal tempB 		: unsigned(width-1 downto 0);
	signal answer 		: unsigned(width-1 downto 0);
	
	begin
		tempB <= b xor (not zeros) when op='1' else b;
		
		summator: for i in 0 to width-1 generate
			adderX: adder port map (a(i), tempB(i), carryOuts(i), answer(i), carryOuts(i+1));
		end generate;

		err <= carryOuts(width) when op='0'
			else '0' when ((carryOuts(width))='1' or ((answer+1)=zeros))
			else '1';

		x <= answer when op='0'
			else (answer+1) when (carryOuts(width))='1'
			else zeros;
end Behavioral;

L2/Subtractor/tb.vhdl
library ieee;
use ieee.std_logic_1164.all;
use ieee.numeric_std.all;

entity subtractor_tb is
end subtractor_tb;

architecture Behavioral of subtractor_tb is

	component subtractor
		generic( width : integer := 5);
		port(
			op : in  std_logic;
			a,b : in unsigned(width-1 downto 0);
			x : out  unsigned(width-1 downto 0);
			err : out  std_logic
		);
	end component;

	signal op : std_logic := '0';
	signal a, b : unsigned(4 downto 0) := (others => '0');
	signal x : unsigned(4 downto 0);
	signal err : std_logic;
BEGIN

	UUT : subtractor generic map (width => 5)
	port map(
		op 	=> op,
		a 	=> a,
		b 	=> b,
		x 	=> x,
		err => err
	);

	process
		begin

		wait for 20 ns;

		op <= '1';
		
		a <= "00000";
		b <= "00000";
		wait for 20 ns;
		
		a <= "11111";
		b <= "11111";
		wait for 20 ns;
		
		a <= "00000";
		b <= "11111";
		wait for 20 ns;
		
		a <= "00001";
		b <= "00100";
		wait for 20 ns;
		
		a <= "10000";
		b <= "00001";
		wait for 20 ns;

		a <= "11100";
		b <= "01011";
		wait for 20 ns;

		op <= '0';
		
		a <= "00000";
		b <= "00000";
		wait for 20 ns;
		
		a <= "11111";
		b <= "11111";
		wait for 20 ns;

		a <= "10101";
		b <= "01010";
		wait for 20 ns;

		wait;
	end process;
end Behavioral;

L2/Subtractor/subtractor.vcd
$date
  Wed Mar 31 09:33:44 2021
$end
$version
  GHDL v0
$end
$timescale
  1 fs
$end
$scope module standard $end
$upscope $end
$scope module std_logic_1164 $end
$upscope $end
$scope module numeric_std $end
$upscope $end
$scope module subtractor_tb $end
$var reg 1 ! op $end
$var reg 5 " a[4:0] $end
$var reg 5 # b[4:0] $end
$var reg 5 $ x[4:0] $end
$var reg 1 % err $end
$scope module uut $end
$var reg 1 & op $end
$var reg 5 ' a[4:0] $end
$var reg 5 ( b[4:0] $end
$var reg 5 ) x[4:0] $end
$var reg 1 * err $end
$var reg 6 + carryouts[5:0] $end
$var reg 5 , tempb[4:0] $end
$var reg 5 - answer[4:0] $end
$scope module summator(0) $end
$scope module adderx $end
$var reg 1 . i0 $end
$var reg 1 / i1 $end
$var reg 1 0 ci $end
$var reg 1 1 s $end
$var reg 1 2 co $end
$upscope $end
$upscope $end
$scope module summator(1) $end
$scope module adderx $end
$var reg 1 3 i0 $end
$var reg 1 4 i1 $end
$var reg 1 5 ci $end
$var reg 1 6 s $end
$var reg 1 7 co $end
$upscope $end
$upscope $end
$scope module summator(2) $end
$scope module adderx $end
$var reg 1 8 i0 $end
$var reg 1 9 i1 $end
$var reg 1 : ci $end
$var reg 1 ; s $end
$var reg 1 < co $end
$upscope $end
$upscope $end
$scope module summator(3) $end
$scope module adderx $end
$var reg 1 = i0 $end
$var reg 1 > i1 $end
$var reg 1 ? ci $end
$var reg 1 @ s $end
$var reg 1 A co $end
$upscope $end
$upscope $end
$scope module summator(4) $end
$scope module adderx $end
$var reg 1 B i0 $end
$var reg 1 C i1 $end
$var reg 1 D ci $end
$var reg 1 E s $end
$var reg 1 F co $end
$upscope $end
$upscope $end
$upscope $end
$upscope $end
$enddefinitions $end
#0
0!
b00000 "
b00000 #
bUUUUU $
U%
0&
b00000 '
b00000 (
bUUUUU )
U*
bUUUUU0 +
b00000 ,
bUUUUU -
0.
0/
00
U1
U2
03
04
U5
U6
U7
08
09
U:
U;
U<
0=
0>
U?
U@
UA
0B
0C
UD
UE
UF
#1000000
bUUUU0 $
0%
bUUUU0 )
0*
b000000 +
bUUUU0 -
01
02
05
U6
07
0:
U;
0<
0?
U@
0A
0D
UE
0F
#2000000
b00000 $
b00000 )
b00000 -
06
07
0;
0<
0@
0A
0E
0F
#20000000
1!
1%
1&
1*
b11111 ,
1/
14
19
1>
1C
#21000000
0%
0*
b11111 -
11
02
16
07
1;
0<
1@
0A
1E
0F
#40000000
b11111 "
b11111 #
b11111 '
b11111 (
b00000 ,
1.
0/
13
04
18
09
1=
0>
1B
0C
#41000000
11
02
16
07
1;
0<
1@
0A
1E
0F
#60000000
b00000 "
b00000 '
0.
03
08
0=
0B
#61000000
1%
1*
b00000 -
01
02
06
07
0;
0<
0@
0A
0E
0F
#80000000
b00001 "
b00100 #
b00001 '
b00100 (
b11011 ,
1.
1/
14
1>
1C
#81000000
b000010 +
b11010 -
01
12
15
16
07
1@
0A
1E
0F
#82000000
b000110 +
b11000 -
06
17
1:
#83000000
b11100 -
1;
0<
#100000000
b10000 "
b00001 #
b10000 '
b00001 (
b11110 ,
0.
0/
19
1B
#101000000
b01001 $
0%
b01001 )
0*
b101100 +
b01000 -
01
02
05
0;
1<
1?
0E
1F
#102000000
b00011 $
b00011 )
b111000 +
b00010 -
16
07
0:
0@
1A
1D
#103000000
b10111 $
b10111 )
b110000 +
b10110 -
1;
0<
0?
1E
1F
#104000000
b11111 $
b11111 )
b100000 +
b11110 -
1@
0A
0D
#105000000
b01111 $
b01111 )
b01110 -
0E
1F
#120000000
b11100 "
b01011 #
b11100 '
b01011 (
b10100 ,
04
18
1=
0>
#121000000
b01001 $
b01001 )
b101000 +
b01000 -
06
07
0;
1<
1?
1@
0A
#122000000
b00001 $
b00001 )
b111000 +
b00000 -
0@
1A
1D
#123000000
b10001 $
b10001 )
b10000 -
1E
1F
#140000000
0!
b00000 "
b00000 #
b10000 $
1%
0&
b00000 '
b00000 (
b10000 )
1*
b00000 ,
08
09
0=
0B
0C
#141000000
b11000 $
0%
b11000 )
0*
b000000 +
b11000 -
0;
0<
0?
1@
0A
0D
1E
0F
#142000000
b00000 $
b00000 )
b00000 -
0@
0A
0E
0F
#160000000
b11111 "
b11111 #
b11111 '
b11111 (
b11111 ,
1.
1/
13
14
18
19
1=
1>
1B
1C
#161000000
1%
1*
b111110 +
01
12
15
06
17
1:
0;
1<
1?
0@
1A
1D
0E
1F
#162000000
b11110 $
b11110 )
b11110 -
16
17
1;
1<
1@
1A
1E
1F
#180000000
b10101 "
b01010 #
b10101 '
b01010 (
b01010 ,
0/
03
09
0=
0C
#181000000
b00001 $
b00001 )
b111100 +
b00001 -
11
02
05
06
17
0;
1<
0@
1A
0E
1F
#182000000
b00011 $
b00011 )
b111000 +
b00011 -
16
07
0:
#183000000
b00111 $
b00111 )
b110000 +
b00111 -
1;
0<
0?
#184000000
b01111 $
b01111 )
b100000 +
b01111 -
1@
0A
0D
#185000000
b11111 $
0%
b11111 )
0*
b000000 +
b11111 -
1E
0F
