L2/lab2-gates.vhd
library IEEE;
use IEEE.STD_LOGIC_1164.ALL;

entity gateAND is
port (
	X: in std_logic;
	Y: in std_logic;
	Z: out std_logic
);
end gateAND;

architecture Behavioral of gateAND is
begin
	Z <= X and Y after 1 ns;
end Behavioral;



-- bramka OR
library IEEE;
use IEEE.STD_LOGIC_1164.ALL;

entity gateOR is
port (
	X: in std_logic;
	Y: in std_logic;
	Z: out std_logic
);
end gateOR;

architecture Behavioral of gateOR is
begin
	Z <= X or Y after 1 ns;
end Behavioral;




-- bramka XOR
library IEEE;
use IEEE.STD_LOGIC_1164.ALL;

entity gateXOR is
port (
	X: in std_logic;
	Y: in std_logic;
	Z: out std_logic
);
end gateXOR;

architecture Behavioral of gateXOR is
begin
	Z <= X xor Y after 1 ns;
end Behavioral;



-- bramka NOT
library IEEE;
use IEEE.STD_LOGIC_1164.ALL;

entity gateNOT is
	port (
	   	X: in std_logic;
		Z: out std_logic
	);
end gateNOT;

architecture Behavioral of gateNOT is
begin
	Z <= not X after 1 ns;
end Behavioral;



-- multiplekser czterowejisciowy
library IEEE;
use IEEE.STD_LOGIC_1164.ALL;

entity mux is
	port (
		a,b,c,d : in std_logic;
		s0,s1   : in std_logic;
		x       : out std_logic
	);
end mux;

architecture zachowanie of mux is
begin
	process (a,b,c,d, s0,s1)
		variable sel: integer;
	begin
		if s0='0' and s1='0' then
			sel := 0;
		elsif s0='1' and s1='1' then
			sel := 1;
		elsif s0='0' and s1='1' then
			sel := 2;
		else
			sel := 3;
		end if;
		case sel is 
			when 0 =>
				x <= a;
			when 1 =>
				x <= b;
			when 2 =>
				x <= c;
			when others =>
				x <= d;
		end case;
	end process;
end zachowanie;

L2/example.vhd
library IEEE;
use IEEE.STD_LOGIC_1164.ALL;


entity example is
	port (
		a,b,c : in std_logic;
		x     : out std_logic
	);
end example;

architecture Synthetic of example is
	component gateNOT
		port (X: in std_logic; 
		      Z: out std_logic);
	end component;

	component gateOR
		port (X,Y: in std_logic;
		        Z: out std_logic);
	end component;

	signal NOT_OR,
		OR_OR,
		OR_NOT : std_logic;
begin
	G1: gateNOT port map (a,NOT_OR);
	G2: gateOR  port map (b,c,OR_OR);
	-- alternatywne sposoby opisu mapowania portow
	--G3: gateOR  port map (NOT_OR,OR_OR,OR_NOT);
	G3: gateOR port map (X => NOT_OR, Y => OR_OR, Z => OR_NOT);
	G4: gateNOT port map (OR_NOT, x);
end Synthetic;

L2/example_tb.vhd
library IEEE;
use IEEE.STD_LOGIC_1164.ALL;
-- jesli mozliwe, nie uzywac std_logic_unsigned -- nie wspiera standardow
--USE ieee.std_logic_unsigned.ALL;
-- numeric_std i owszem
use IEEE.NUMERIC_STD.ALL;
 
 
ENTITY example_tb IS
END example_tb;
 
ARCHITECTURE behavior OF example_tb IS 
    -- deklaracja komponentu Unit Under Test (UUT)
	COMPONENT example
	PORT(
		a : IN  std_logic;
		b : IN  std_logic;
		c : IN  std_logic;
		x : OUT  std_logic
	);
	END COMPONENT;

   	-- inputs
	signal a : std_logic := '0';
	signal b : std_logic := '0';
	signal c : std_logic := '0';
	
	-- sprawdz dzialanie obu ponizszych, alternatywnych deklaracji
	-- signal abc : std_logic_vector(2 downto 0) := (others => '0');
	signal abc : unsigned(2 downto 0) := (others => '0');

   	--Outputs
	signal x : std_logic;

	-- okres zegara
	constant period : time := 10 ns;
 
BEGIN
	-- instantiate the Unit Under Test (UUT)
	uut: example PORT MAP (
		a => a,
		b => b,
		c => c,
		x => x
	);

	-- Stimulus process
	stim_proc: process
	begin		
		-- hold reset state for 100 ns.
		wait for 100 ns;	

		wait for period*10;

		-- silly way to test all states... 
		a <= '0';
		b <= '0';
		c <= '1';
		wait for period;
			
		a <= '0';
		b <= '1';
		c <= '0';
		wait for period;

		a <= '0';
		b <= '1';
		c <= '1';
		wait for period;

		a <= '1';
		b <= '0';
		c <= '0';
		wait for period;

		a <= '1';
		b <= '0';
		c <= '1';
		wait for period;

		a <= '1';
		b <= '1';
		c <= '0';
		wait for period;

		a <= '1';
		b <= '1';
		c <= '1';

		wait for 10*period;
			
		-- another way to do this... 
		for i in 0 to 6 loop
		-- w zaleznosci od tego, jak zadeklarowano sygnal 'abc',
		--     mozna go zwiekszyc na rozne sposoby
		-- sprawdz, ktory pasuje do ktorej deklaracji
		--  ten:
		-- abc <= std_logic_vector( unsigned(abc) + 1 );
		--  i ten:
			abc <= abc + 1;
			a <= abc(2);
			b <= abc(1);
			c <= abc(0);
			wait for period;
		end loop;
		wait;
	end process;
END;

L2/example1.vcd
$date
  Wed Mar 24 00:10:21 2021
$end
$version
  GHDL v0
$end
$timescale
  1 fs
$end
$scope module standard $end
$upscope $end
$scope module std_logic_1164 $end
$upscope $end
$scope module numeric_std $end
$upscope $end
$scope module example_tb $end
$var reg 1 ! a $end
$var reg 1 " b $end
$var reg 1 # c $end
$var reg 3 $ abc[2:0] $end
$var reg 1 % x $end
$scope module uut $end
$var reg 1 & a $end
$var reg 1 ' b $end
$var reg 1 ( c $end
$var reg 1 ) x $end
$var reg 1 * not_or $end
$var reg 1 + or_or $end
$var reg 1 , or_not $end
$scope module g1 $end
$var reg 1 - x $end
$var reg 1 . z $end
$upscope $end
$scope module g2 $end
$var reg 1 / x $end
$var reg 1 0 y $end
$var reg 1 1 z $end
$upscope $end
$scope module g3 $end
$var reg 1 2 x $end
$var reg 1 3 y $end
$var reg 1 4 z $end
$upscope $end
$scope module g4 $end
$var reg 1 5 x $end
$var reg 1 6 z $end
$upscope $end
$upscope $end
$upscope $end
$enddefinitions $end
#0
0!
0"
0#
b000 $
U%
0&
0'
0(
U)
U*
U+
U,
0-
U.
0/
00
U1
U2
U3
U4
U5
U6
#1000000
U)
1*
0+
1.
01
12
03
U4
U6
#2000000
1,
14
15
#3000000
0%
0)
06
#100000000
#200000000
1#
1(
10
#201000000
1+
11
13
#202000000
14
#210000000
1"
0#
1'
0(
1/
00
#211000000
11
#220000000
1#
1(
10
#221000000
11
#230000000
1!
0"
0#
1&
0'
0(
1-
0/
00
#231000000
0*
0+
0.
01
02
03
#232000000
0,
04
05
#233000000
1%
1)
16
#240000000
1#
1(
10
#241000000
1+
11
13
#242000000
1,
14
15
#243000000
0%
0)
06
#250000000
1"
0#
1'
0(
1/
00
#251000000
11
#260000000
1#
1(
10
#261000000
11
#360000000
0!
0"
0#
b001 $
0&
0'
0(
0-
0/
00
#361000000
1*
0+
1.
01
12
03
#362000000
14
#370000000
1#
b010 $
1(
10
#371000000
1+
11
13
#372000000
14
#380000000
1"
0#
b011 $
1'
0(
1/
00
#381000000
11
#390000000
1#
b100 $
1(
10
#391000000
11
#400000000
1!
0"
0#
b101 $
1&
0'
0(
1-
0/
00
#401000000
0*
0+
0.
01
02
03
#402000000
0,
04
05
#403000000
1%
1)
16
#410000000
1#
b110 $
1(
10
#411000000
1+
11
13
#412000000
1,
14
15
#413000000
0%
0)
06
#420000000
1"
0#
b111 $
1'
0(
1/
00
#421000000
11
